<?xml version="1.0" encoding="UTF-8" ?>
<!DOCTYPE mapper PUBLIC "-//mybatis.org//DTD Mapper 3.0//EN" "http://mybatis.org/dtd/mybatis-3-mapper.dtd" >
<mapper namespace="com.isea533.mybatis.mapper.UserLoginInfoMapper" >
  <resultMap id="BaseResultMap" type="com.isea533.mybatis.model.UserLoginInfo" >
    <!--
      WARNING - @mbggenerated
      This element is automatically generated by MyBatis Generator, do not modify.
      This element was generated on Wed Aug 26 20:55:40 CST 2015.
    -->
    <id column="Id" property="id" jdbcType="INTEGER" />
    <id column="username" property="username" jdbcType="VARCHAR" />
    <result column="logindate" property="logindate" jdbcType="TIMESTAMP" />
    <result column="loginip" property="loginip" jdbcType="VARCHAR" />
  </resultMap>
  <delete id="deleteByPrimaryKey" parameterType="map" >
    <!--
      WARNING - @mbggenerated
      This element is automatically generated by MyBatis Generator, do not modify.
      This element was generated on Wed Aug 26 20:55:40 CST 2015.
    -->
    delete from user login info
    where Id = #{id,jdbcType=INTEGER}
      and username = #{username,jdbcType=VARCHAR}
  </delete>
  <insert id="insert" parameterType="com.isea533.mybatis.model.UserLoginInfo" >
    <!--
      WARNING - @mbggenerated
      This element is automatically generated by MyBatis Generator, do not modify.
      This element was generated on Wed Aug 26 20:55:40 CST 2015.
    -->
    <selectKey resultType="java.lang.Integer" keyProperty="id" order="AFTER" >
      SELECT LAST_INSERT_ID()
    </selectKey>
    insert into user login info (username, logindate, loginip
      )
    values (#{username,jdbcType=VARCHAR}, #{logindate,jdbcType=TIMESTAMP}, #{loginip,jdbcType=VARCHAR}
      )
  </insert>
  <update id="updateByPrimaryKey" parameterType="com.isea533.mybatis.model.UserLoginInfo" >
    <!--
      WARNING - @mbggenerated
      This element is automatically generated by MyBatis Generator, do not modify.
      This element was generated on Wed Aug 26 20:55:40 CST 2015.
    -->
    update user login info
    set logindate = #{logindate,jdbcType=TIMESTAMP},
      loginip = #{loginip,jdbcType=VARCHAR}
    where Id = #{id,jdbcType=INTEGER}
      and username = #{username,jdbcType=VARCHAR}
  </update>
  <select id="selectByPrimaryKey" resultMap="BaseResultMap" parameterType="map" >
    <!--
      WARNING - @mbggenerated
      This element is automatically generated by MyBatis Generator, do not modify.
      This element was generated on Wed Aug 26 20:55:40 CST 2015.
    -->
    select Id, username, logindate, loginip
    from user login info
    where Id = #{id,jdbcType=INTEGER}
      and username = #{username,jdbcType=VARCHAR}
  </select>
  <select id="selectAll" resultMap="BaseResultMap" >
    <!--
      WARNING - @mbggenerated
      This element is automatically generated by MyBatis Generator, do not modify.
      This element was generated on Wed Aug 26 20:55:40 CST 2015.
    -->
    select Id, username, logindate, loginip
    from user login info
  </select>
</mapper>